alphabet2kana/__init__.py
alphabet2kana/alphabet2kana.py
alphabet2kana/char_table.py
alphabet2kana/main.py
alphabet2kana-0.1.7.dist-info/LICENSE
alphabet2kana-0.1.7.dist-info/METADATA
alphabet2kana-0.1.7.dist-info/WHEEL
alphabet2kana-0.1.7.dist-info/entry_points.txt
alphabet2kana-0.1.7.dist-info/RECORD
