Metadata-Version: 2.3
Name: alphabet2kana
Version: 0.1.7
Summary: Convert English alphabet to Katakana
Author: shihono
Author-email: 26952997+shihono@users.noreply.github.com
Requires-Python: >=3.9,<4.0
Classifier: Programming Language :: Python :: 3
Classifier: Programming Language :: Python :: 3.9
Classifier: Programming Language :: Python :: 3.10
Classifier: Programming Language :: Python :: 3.11
Classifier: Programming Language :: Python :: 3.12
Classifier: Programming Language :: Python :: 3.13
Project-URL: Repository, https://github.com/shihono/alphabet2kana
